{"trials": [{"task": "44", "solutions": {"8182": "compositional", "3173": "bespoke", "6353": "bespoke", "1716": "bespoke", "9669": "bespoke", "9756": "bespoke", "9183": "bespoke", "7924": "bespoke", "3148": "bespoke", "3926": "bespoke", "3848": "bespoke", "3611": "bespoke", "6625": "bespoke", "8829": "bespoke", "9498": "bespoke", "1513": "bespoke", "6121": "bespoke", "4576": "bespoke", "5238": "bespoke", "7657": "bespoke"}, "blockString": "_1__22\n111__2\n1_1222\n111__2\n_1__22"}, {"task": "24", "solutions": {"5682": "compositional", "3592": "bespoke", "2819": "bespoke", "1796": "bespoke", "5854": "bespoke", "7698": "bespoke", "4738": "bespoke", "6345": "bespoke", "6387": "bespoke", "7135": "bespoke", "6646": "bespoke", "5395": "bespoke", "1633": "bespoke", "3523": "bespoke", "4159": "bespoke", "7228": "bespoke", "7332": "bespoke", "8733": "bespoke", "3221": "bespoke", "1539": "bespoke"}, "blockString": "111_22\n__1__2\n_11222\n__1__2\n111_22"}, {"task": "21", "solutions": {"5627": "compositional", "3755": "bespoke", "2945": "bespoke", "2997": "bespoke", "5783": "bespoke", "3874": "bespoke", "9737": "bespoke", "8471": "bespoke", "1799": "bespoke", "3779": "bespoke", "3914": "bespoke", "9187": "bespoke", "2422": "bespoke", "4236": "bespoke", "8664": "bespoke", "5163": "bespoke", "7782": "bespoke", "4339": "bespoke", "8156": "bespoke", "6978": "bespoke"}, "blockString": "111___\n__1_22\n_11222\n__1_22\n111___"}, {"task": "22", "solutions": {"5633": "compositional", "3388": "bespoke", "1764": "bespoke", "4572": "bespoke", "3368": "bespoke", "2616": "bespoke", "2243": "bespoke", "6623": "bespoke", "9996": "bespoke", "2459": "bespoke", "2125": "bespoke", "2785": "bespoke", "8886": "bespoke", "3149": "bespoke", "2192": "bespoke", "9451": "bespoke", "4879": "bespoke", "4686": "bespoke", "8144": "bespoke", "1399": "bespoke"}, "blockString": "111__2\n__1__2\n_11222\n__1__2\n111__2"}, {"task": "13", "solutions": {"5521": "compositional", "6256": "bespoke", "7297": "bespoke", "6763": "bespoke", "8611": "bespoke", "9863": "bespoke", "6655": "bespoke", "5866": "bespoke", "2711": "bespoke", "3582": "bespoke", "7664": "bespoke", "7599": "bespoke", "9236": "bespoke", "5214": "bespoke", "1898": "bespoke", "8577": "bespoke", "3852": "bespoke", "3645": "bespoke", "2457": "bespoke", "4784": "bespoke"}, "blockString": "111__2\n1_1_22\n11122_\n1_1_22\n111__2"}, {"task": "32", "solutions": {"2433": "compositional", "2359": "bespoke", "4931": "bespoke", "2282": "bespoke", "3979": "bespoke", "9435": "bespoke", "4263": "bespoke", "5792": "bespoke", "2779": "bespoke", "8147": "bespoke", "8191": "bespoke", "3186": "bespoke", "4691": "bespoke", "4732": "bespoke", "3529": "bespoke", "6938": "bespoke", "3536": "bespoke", "5743": "bespoke", "3323": "bespoke", "9168": "bespoke"}, "blockString": "__1__2\n_11__2\n111222\n_11__2\n__1__2"}, {"task": "12", "solutions": {"5533": "compositional", "3922": "bespoke", "9238": "bespoke", "4366": "bespoke", "6158": "bespoke", "6532": "bespoke", "5293": "bespoke", "1435": "bespoke", "1187": "bespoke", "1424": "bespoke", "6366": "bespoke", "7525": "bespoke", "9568": "bespoke", "9935": "bespoke", "1193": "bespoke", "5292": "bespoke", "9622": "bespoke", "3136": "bespoke", "3581": "bespoke", "3395": "bespoke"}, "blockString": "111__2\n1_1__2\n111222\n1_1__2\n111__2"}, {"task": "33", "solutions": {"2421": "compositional", "3266": "bespoke", "5619": "bespoke", "9134": "bespoke", "5653": "bespoke", "6571": "bespoke", "6832": "bespoke", "4884": "bespoke", "2576": "bespoke", "9895": "bespoke", "9287": "bespoke", "9868": "bespoke", "6271": "bespoke", "1571": "bespoke", "2647": "bespoke", "5476": "bespoke", "2391": "bespoke", "1644": "bespoke", "7177": "bespoke", "9513": "bespoke"}, "blockString": "__1__2\n_11_22\n11122_\n_11_22\n__1__2"}], "params": {"width": 6, "height": 5, "maxDigit": 9, "codeLength": 4, "nPart": 4, "solutionsPerTask": 20, "manual": [{"task": "33", "compositional": false, "blockString": "__3__3\n_33_33\n33333_\n_33_33\n__3__3", "code": "3266"}, {"task": "12", "compositional": true, "blockString": "111__2\n1_1__2\n111222\n1_1__2\n111__2", "code": "5533"}, {"task": "31", "compositional": true, "blockString": "__1___\n_11_22\n111222\n_11_22\n__1___", "code": "2427"}, {"task": "13", "compositional": false, "blockString": "333__3\n3_3_33\n33333_\n3_3_33\n333__3", "code": "6256"}, {"task": "33", "compositional": true, "blockString": "__1__2\n_11_22\n11122_\n_11_22\n__1__2", "code": "2421"}, {"task": "44", "compositional": false, "blockString": "_3__33\n333__3\n3_3333\n333__3\n_3__33", "code": "3173"}, {"task": "22", "compositional": false, "blockString": "333__3\n__3__3\n_33333\n__3__3\n333__3", "code": "3388"}]}, "instructions": {"params": {"width": 6, "height": 3, "maxDigit": 4}, "shapes": {"11": "111__2\n1_1222\n111__2", "12": "111_22\n1_122_\n111_22", "13": "111_2_\n1_1222\n111_2_", "14": "111_22\n1_1222\n111_22", "21": "111__2\n__1222\n111__2", "22": "111_22\n__122_\n111_22", "23": "111_2_\n__1222\n111_2_", "24": "111_22\n__1222\n111_22", "31": "111__2\n111222\n111__2", "32": "111_22\n11122_\n111_22", "33": "111_2_\n111222\n111_2_", "34": "111_22\n111222\n111_22", "41": "__1__2\n111222\n__1__2", "42": "__1_22\n11122_\n__1_22", "43": "__1_2_\n111222\n__1_2_", "44": "__1_22\n111222\n__1_22"}, "codes": {"11": {"compositional": "2124", "bespoke": "3131"}, "12": {"compositional": "2144", "bespoke": "1213"}, "13": {"compositional": "2111", "bespoke": "3231"}, "14": {"compositional": "2131", "bespoke": "3123"}, "21": {"compositional": "1224", "bespoke": "4242"}, "22": {"compositional": "1244", "bespoke": "1133"}, "23": {"compositional": "1211", "bespoke": "2113"}, "24": {"compositional": "1231", "bespoke": "4143"}, "31": {"compositional": "1324", "bespoke": "3133"}, "32": {"compositional": "1344", "bespoke": "4124"}, "33": {"compositional": "1311", "bespoke": "3223"}, "34": {"compositional": "1331", "bespoke": "1121"}, "41": {"compositional": "4324", "bespoke": "3111"}, "42": {"compositional": "4344", "bespoke": "2143"}, "43": {"compositional": "4311", "bespoke": "4244"}, "44": {"compositional": "4331", "bespoke": "4134"}}}}