{"trials": [{"task": "43", "solutions": {"8817": "compositional", "3648": "bespoke", "5349": "bespoke", "5171": "bespoke", "3451": "bespoke", "5459": "bespoke", "9323": "bespoke", "1937": "bespoke", "7593": "bespoke", "3838": "bespoke", "5548": "bespoke", "8232": "bespoke", "7286": "bespoke", "2993": "bespoke", "9284": "bespoke", "1627": "bespoke", "6188": "bespoke", "5767": "bespoke", "6944": "bespoke", "8245": "bespoke"}, "blockString": "_1___2\n111_22\n1_122_\n111_22\n_1___2"}, {"task": "33", "solutions": {"2617": "compositional", "6226": "bespoke", "4943": "bespoke", "6122": "bespoke", "3995": "bespoke", "1264": "bespoke", "3237": "bespoke", "9541": "bespoke", "1454": "bespoke", "7943": "bespoke", "3747": "bespoke", "5363": "bespoke", "5465": "bespoke", "5858": "bespoke", "3646": "bespoke", "8876": "bespoke", "5816": "bespoke", "4242": "bespoke", "2563": "bespoke", "1597": "bespoke"}, "blockString": "__1__2\n_11_22\n11122_\n_11_22\n__1__2"}, {"task": "31", "solutions": {"2664": "compositional", "2525": "bespoke", "4752": "bespoke", "2373": "bespoke", "6281": "bespoke", "3815": "bespoke", "1979": "bespoke", "7347": "bespoke", "8126": "bespoke", "1814": "bespoke", "8467": "bespoke", "1489": "bespoke", "3466": "bespoke", "5862": "bespoke", "7284": "bespoke", "7759": "bespoke", "6173": "bespoke", "9456": "bespoke", "7336": "bespoke", "3537": "bespoke"}, "blockString": "__1___\n_11_22\n111222\n_11_22\n__1___"}, {"task": "23", "solutions": {"2517": "compositional", "3311": "bespoke", "8955": "bespoke", "9869": "bespoke", "7753": "bespoke", "5944": "bespoke", "4878": "bespoke", "4893": "bespoke", "5347": "bespoke", "8785": "bespoke", "8439": "bespoke", "3522": "bespoke", "3634": "bespoke", "6725": "bespoke", "1589": "bespoke", "4648": "bespoke", "5883": "bespoke", "8622": "bespoke", "3535": "bespoke", "5427": "bespoke"}, "blockString": "111__2\n__1_22\n_1122_\n__1_22\n111__2"}, {"task": "11", "solutions": {"7164": "compositional", "5149": "bespoke", "8734": "bespoke", "7765": "bespoke", "9591": "bespoke", "7739": "bespoke", "2323": "bespoke", "1395": "bespoke", "1396": "bespoke", "1346": "bespoke", "3417": "bespoke", "2115": "bespoke", "9792": "bespoke", "4216": "bespoke", "9994": "bespoke", "6118": "bespoke", "1216": "bespoke", "8168": "bespoke", "6488": "bespoke", "3618": "bespoke"}, "blockString": "111___\n1_1_22\n111222\n1_1_22\n111___"}, {"task": "12", "solutions": {"7111": "compositional", "5989": "bespoke", "9287": "bespoke", "6841": "bespoke", "1446": "bespoke", "7981": "bespoke", "6759": "bespoke", "3962": "bespoke", "3834": "bespoke", "1141": "bespoke", "1481": "bespoke", "5129": "bespoke", "5352": "bespoke", "6441": "bespoke", "3525": "bespoke", "4723": "bespoke", "8828": "bespoke", "3828": "bespoke", "6556": "bespoke", "5931": "bespoke"}, "blockString": "111__2\n1_1__2\n111222\n1_1__2\n111__2"}, {"task": "21", "solutions": {"2564": "compositional", "7154": "bespoke", "3339": "bespoke", "8912": "bespoke", "3188": "bespoke", "8448": "bespoke", "2633": "bespoke", "1893": "bespoke", "2482": "bespoke", "7277": "bespoke", "7282": "bespoke", "9713": "bespoke", "6958": "bespoke", "5215": "bespoke", "5845": "bespoke", "7714": "bespoke", "1586": "bespoke", "7433": "bespoke", "3617": "bespoke", "8452": "bespoke"}, "blockString": "111___\n__1_22\n_11222\n__1_22\n111___"}, {"task": "14", "solutions": {"7172": "compositional", "2413": "bespoke", "8492": "bespoke", "1758": "bespoke", "6713": "bespoke", "7529": "bespoke", "9773": "bespoke", "9234": "bespoke", "4796": "bespoke", "5297": "bespoke", "4966": "bespoke", "5441": "bespoke", "8247": "bespoke", "8698": "bespoke", "2221": "bespoke", "3556": "bespoke", "2574": "bespoke", "6192": "bespoke", "1983": "bespoke", "5748": "bespoke"}, "blockString": "111_22\n1_1__2\n111222\n1_1__2\n111_22"}], "params": {"width": 6, "height": 5, "maxDigit": 9, "codeLength": 4, "nPart": 4, "solutionsPerTask": 20, "manual": [{"task": "22", "compositional": true, "blockString": "111__2\n__1__2\n_11222\n__1__2\n111__2", "code": "2511"}, {"task": "21", "compositional": true, "blockString": "111___\n__1_22\n_11222\n__1_22\n111___", "code": "2564"}, {"task": "12", "compositional": false, "blockString": "333__3\n3_3__3\n333333\n3_3__3\n333__3", "code": "5989"}, {"task": "23", "compositional": false, "blockString": "333__3\n__3_33\n_3333_\n__3_33\n333__3", "code": "3311"}, {"task": "14", "compositional": true, "blockString": "111_22\n1_1__2\n111222\n1_1__2\n111_22", "code": "7172"}, {"task": "33", "compositional": false, "blockString": "__3__3\n_33_33\n33333_\n_33_33\n__3__3", "code": "6226"}, {"task": "14", "compositional": false, "blockString": "333_33\n3_3__3\n333333\n3_3__3\n333_33", "code": "2413"}], "maxTry": 228.0, "maxTryPartial": 56.0}, "instructions": {"params": {"width": 6, "height": 3, "maxDigit": 4}, "shapes": {"11": "111__2\n1_1222\n111__2", "12": "111_22\n1_122_\n111_22", "13": "111_2_\n1_1222\n111_2_", "21": "111__2\n__1222\n111__2", "22": "111_22\n__122_\n111_22", "23": "111_2_\n__1222\n111_2_", "31": "111__2\n111222\n111__2", "32": "111_22\n11122_\n111_22", "33": "111_2_\n111222\n111_2_"}, "codes": {"11": {"compositional": "2432", "bespoke": "2141"}, "12": {"compositional": "2414", "bespoke": "3243"}, "13": {"compositional": "2441", "bespoke": "1114"}, "21": {"compositional": "3332", "bespoke": "4111"}, "22": {"compositional": "3314", "bespoke": "1132"}, "23": {"compositional": "3341", "bespoke": "4144"}, "31": {"compositional": "2232", "bespoke": "3213"}, "32": {"compositional": "2214", "bespoke": "4441"}, "33": {"compositional": "2241", "bespoke": "4414"}}}}